{"category": "House", "address": "Trekwei 7", "neighborhood": "Workum", "city": "Workum", "postcode": "8711GR", "province": "Friesland", "Aanvaarding": "In overleg", "Status": "Beschikbaar", "Aangeboden sinds": "04/09/2024", "Oorspronkelijke vraagprijs": 845000.0, "Vraagprijs per m\u00b2": 4595.0, "Vraagprijs": 795000.0, "Soort dak": "Zadeldak bedekt met pannen", "Bouwjaar": 0, "Soort bouw": "Bestaande bouw", "Soort woonhuis": "Eengezinswoning, vrijstaande woning", "Inhoud": 1.9, "Perceel": 3.292, "Externe bergruimte": 62.0, "Overige inpandige ruimte": 291.0, "Wonen": 173.0, "Voorzieningen": "Elektra, verwarming en stromend water", "Aantal woonlagen": "2 woonlagen", "Badkamervoorzieningen": "Ligbad, toilet, en wastafelmeubel", "Aantal badkamers": "1 badkamer", "Cv-ketel": "HR Intergas (gas gestookt combiketel uit 2024, eigendom)", "Warm water": "Cv-ketel", "Verwarming": "Cv-ketel", "Isolatie": "Gedeeltelijk dubbel glas", "Energielabel": "Niet", "Eigendomssituatie": "Volle eigendom", "Oppervlakte": 2.358, "Tuin": "Tuin rondom", "Ligging": "Aan rustige weg, aan vaarwater, aan water, in centrum en vrij uitzicht", "Schuur/berging": "Inpandig", "Capaciteit": "1 auto", "Soort garage": "Vrijstaande stenen garage", "Soort parkeergelegenheid": "Op eigen terrein", "link": "https://www.funda.nl/detail/koop/workum/huis-trekwei-7/42277812/", "ID": 42277812, "Kamers": 4, "Slaapkamers": 2}