{"category": "Apartment", "address": "High5 - San Francisco MB01 appartementen (Bouwnr. 29)", "neighborhood": "Winkelcentrum Schalkwijk", "city": "Haarlem", "postcode": "2037AR", "province": "Noord-Holland", "Bijdrage VvE": 0.0, "Aanvaarding": "In overleg", "Status": "Onder optie", "Aangeboden sinds": "04/09/2024", "Vraagprijs per m\u00b2": 5749.0, "Vraagprijs": 321961.0, "Keurmerken": "Woningborg Garantiecertificaat", "Soort dak": "Plat dak", "Bouwjaar": 2024, "Soort bouw": "Nieuwbouw", "Soort appartement": "Portiekflat (appartement)", "Inhoud": 146.0, "Gebouwgebonden buitenruimte": 7.0, "Wonen": 56.0, "Voorzieningen": "Balansventilatie en lift", "Gelegen op": "6e woonlaag", "Aantal woonlagen": "1 woonlaag", "Aantal badkamers": "1 badkamer en 1 apart toilet", "Verwarming": "Gehele vloerverwarming en warmtepomp", "Isolatie": "Volledig ge\u00efsoleerd", "Energielabel": "A3", "Balkon/dakterras": "Balkon aanwezig", "Ligging": "Aan rustige weg, in centrum en in woonwijk", "link": "https://www.funda.nl/detail/koop/haarlem/appartement-high5-san-francisco-mb01-appartementen-0-ong/43419188/", "ID": 43419188, "Kamers": 2, "Slaapkamers": 1}