{"category": "Apartment", "address": "High5 - San Francisco MM02 stadswoningen (Bouwnr. 4)", "neighborhood": "Winkelcentrum Schalkwijk", "city": "Haarlem", "postcode": "2037AR", "province": "Noord-Holland", "Bijdrage VvE": 0.0, "Aanvaarding": "In overleg", "Status": "Beschikbaar", "Aangeboden sinds": "04/09/2024", "Vraagprijs per m\u00b2": 5150.0, "Vraagprijs": 515000.0, "Keurmerken": "Woningborg Garantiecertificaat", "Soort dak": "Plat dak", "Bouwjaar": 2024, "Soort bouw": "Nieuwbouw", "Soort appartement": "Maisonnette (appartement)", "Inhoud": 260.0, "Gebouwgebonden buitenruimte": 25.0, "Wonen": 100.0, "Voorzieningen": "Balansventilatie", "Aantal woonlagen": "1 woonlaag", "Badkamervoorzieningen": "Douche, toilet, en wastafel", "Aantal badkamers": "1 badkamer en 1 apart toilet", "Verwarming": "Gehele vloerverwarming en warmtepomp", "Isolatie": "Volledig ge\u00efsoleerd", "Energielabel": "A3", "Balkon/dakterras": "Balkon aanwezig", "Tuin": "Zonneterras", "Ligging": "Aan rustige weg, in centrum en in woonwijk", "Soort garage": "Parkeerplaats", "link": "https://www.funda.nl/detail/koop/haarlem/appartement-high5-san-francisco-mm02-stadswoningen-0-ong/43419056/", "ID": 43419056, "Kamers": 4, "Slaapkamers": 2}