{"category": "Apartment", "address": "Egelantiersstraat 128-B", "neighborhood": "Anjeliersbuurt-Zuid", "city": "Amsterdam", "postcode": "1015PR", "province": "Noord-Holland", "Bijdrage VvE": 108.0, "Status": "Verkocht", "Vraagprijs per m\u00b2": 10128.0, "Laatste vraagprijs": 395000.0, "Soort dak": "Mansarde dak", "Specifiek": "Beschermd stads- of dorpsgezicht en gestoffeerd", "Bouwjaar": 1914, "Soort bouw": "Bestaande bouw", "Soort appartement": "Bovenwoning (appartement)", "Inhoud": 117.0, "Wonen": 39.0, "Voorzieningen": "Frans balkon en mechanische ventilatie", "Gelegen op": "2e woonlaag", "Aantal woonlagen": "1 woonlaag", "Aantal badkamers": "1 badkamer en 1 apart toilet", "Cv-ketel": "Remeha Avanta (gas gestookt combiketel uit 2017, eigendom)", "Warm water": "Cv-ketel", "Verwarming": "Cv-ketel", "Isolatie": "Gedeeltelijk dubbel glas", "Energielabel": "C", "Eigendomssituatie": "Volle eigendom", "Balkon/dakterras": "Frans balkon aanwezig", "Ligging": "In centrum", "Soort parkeergelegenheid": "Betaald parkeren, openbaar parkeren en parkeervergunningen", "Opstalverzekering": "Ja", "Onderhoudsplan": "Nee", "Reservefonds aanwezig": "Ja", "Periodieke bijdrage": 0, "Jaarlijkse vergadering": "Ja", "Inschrijving KvK": "Ja", "Aangeboden sinds": "02/02/2024", "Verkoopdatum": "22/02/2024", "Looptijd": "2 weken", "link": "https://www.funda.nl/detail/koop/amsterdam/appartement-egelantiersstraat-128-b/43476002/", "ID": 43476002, "Kamers": 2, "Slaapkamers": 1}