{"category": "Apartment", "address": "Willem Schoutenstraat 22-2", "neighborhood": "Balboaplein e.o.", "city": "Amsterdam", "postcode": "1057DN", "province": "Noord-Holland", "Bijdrage VvE": 173.0, "Status": "Verkocht", "Vraagprijs per m\u00b2": 8333.0, "Laatste vraagprijs": 375000.0, "Bouwjaar": 1924, "Soort bouw": "Bestaande bouw", "Soort appartement": "Bovenwoning (appartement)", "Inhoud": 142.0, "Gebouwgebonden buitenruimte": 3.0, "Wonen": 45.0, "Aantal woonlagen": "1 woonlaag", "Badkamervoorzieningen": "Douche en toilet", "Aantal badkamers": "1 badkamer", "Cv-ketel": "Eigendom", "Warm water": "Cv-ketel", "Verwarming": "Cv-ketel", "Energielabel": "D", "Lasten": "Eeuwigdurend afgekocht", "Eigendomssituatie": "Gemeentelijke erfpacht", "Balkon/dakterras": "Balkon aanwezig", "Opstalverzekering": "Nee", "Onderhoudsplan": "Nee", "Reservefonds aanwezig": "Nee", "Periodieke bijdrage": "Nee", "Jaarlijkse vergadering": "Nee", "Inschrijving KvK": "Nee", "Aangeboden sinds": "22/05/2024", "Verkoopdatum": "10/06/2024", "Looptijd": "2 weken", "link": "https://www.funda.nl/detail/koop/amsterdam/appartement-willem-schoutenstraat-22-2/43505026/", "ID": 43505026, "Kamers": 3, "Slaapkamers": 2}