{"category": "Apartment", "address": "Lindengracht 59-2", "neighborhood": "Anjeliersbuurt-Noord", "city": "Amsterdam", "postcode": "1015KC", "province": "Noord-Holland", "Bijdrage VvE": 108.36, "Status": "Verkocht", "Vraagprijs per m\u00b2": 8537.0, "Laatste vraagprijs": 350000.0, "Bouwjaar": 1918, "Soort bouw": "Bestaande bouw", "Soort appartement": "Tussenverdieping (appartement)", "Inhoud": 108.0, "Wonen": 41.0, "Voorzieningen": "TV kabel", "Gelegen op": "2e woonlaag", "Aantal woonlagen": "1 woonlaag", "Badkamervoorzieningen": "Douche, toilet, en wastafel", "Aantal badkamers": "1 badkamer", "Cv-ketel": "Intergas (gas gestookt uit 2008, eigendom)", "Warm water": "Cv-ketel", "Verwarming": "Cv-ketel", "Isolatie": "Dubbel glas", "Energielabel": "B", "Eigendomssituatie": "Volle eigendom", "Ligging": "In centrum en in woonwijk", "Opstalverzekering": "Ja", "Onderhoudsplan": "Nee", "Reservefonds aanwezig": "Ja", "Periodieke bijdrage": 0, "Jaarlijkse vergadering": "Ja", "Inschrijving KvK": "Ja", "Aangeboden sinds": "16/06/2024", "Verkoopdatum": "05/07/2024", "Looptijd": "2 weken", "link": "https://www.funda.nl/detail/koop/amsterdam/appartement-lindengracht-59-2/43539044/", "ID": 43539044, "Kamers": 3, "Slaapkamers": 2}