{"category": "Apartment", "address": "Spaarne 38-B", "neighborhood": "Binnenstad", "city": "Haarlem", "postcode": "2011CJ", "province": "Noord-Holland", "Bijdrage VvE": 150.0, "Aanvaarding": "In overleg", "Status": "Beschikbaar", "Aangeboden sinds": "04/09/2024", "Oorspronkelijke vraagprijs": 900000.0, "Vraagprijs per m\u00b2": 5779.0, "Vraagprijs": 890000.0, "Soort dak": "Samengesteld dak bedekt met bitumineuze dakbedekking en pannen", "Specifiek": "Monumentaal pand", "Bouwjaar": 1800, "Soort bouw": "Bestaande bouw", "Soort appartement": "Bovenwoning", "Inhoud": 439.0, "Gebouwgebonden buitenruimte": 15.0, "Wonen": 154.0, "Voorzieningen": "Elektra", "Gelegen op": "3e woonlaag", "Aantal woonlagen": "2 woonlagen", "Badkamervoorzieningen": "Dubbele wastafel, inloopdouche, ligbad, toilet, en wastafelmeubel", "Aantal badkamers": "1 badkamer en 1 apart toilet", "Cv-ketel": "Gas gestookt combiketel, eigendom", "Warm water": "Cv-ketel", "Verwarming": "Cv-ketel", "Isolatie": "Dakisolatie, dubbel glas, muurisolatie, vloerisolatie en volledig ge\u00efsoleerd", "Energielabel": "B", "Eigendomssituatie": "Volle eigendom", "Balkon/dakterras": "Dakterras aanwezig", "Ligging": "Aan vaarwater, aan water, in centrum, in woonwijk en vrij uitzicht", "Schuur/berging": "Box", "Soort parkeergelegenheid": "Betaald parkeren en parkeervergunningen", "Opstalverzekering": "Ja", "Onderhoudsplan": "Nee", "Reservefonds aanwezig": "Ja", "Periodieke bijdrage": 0, "Jaarlijkse vergadering": "Ja", "Inschrijving KvK": "Ja", "link": "https://www.funda.nl/detail/koop/haarlem/appartement-spaarne-38-b/43597789/", "ID": 43597789, "Kamers": 4, "Slaapkamers": 3}