{"category": "House", "address": "Westerstraat 268", "neighborhood": "Anjeliersbuurt-Noord", "city": "Amsterdam", "postcode": "1015MT", "province": "Noord-Holland", "Status": "Verkocht", "Vraagprijs per m\u00b2": 8716.0, "Laatste vraagprijs": 950000.0, "Soort dak": "Samengesteld dak bedekt met bitumineuze dakbedekking en pannen", "Specifiek": "Beschermd stads- of dorpsgezicht en monument", "Bouwjaar": 1800, "Soort bouw": "Bestaande bouw", "Soort woonhuis": "Herenhuis, tussenwoning", "Inhoud": 387.0, "Perceel": 43.0, "Gebouwgebonden buitenruimte": 12.0, "Overige inpandige ruimte": 7.0, "Wonen": 109.0, "Voorzieningen": "TV kabel", "Aantal woonlagen": "4 woonlagen en een vliering", "Badkamervoorzieningen": "Dubbele wastafel, inloopdouche, 2 wastafelmeubels, ligbad, toilet, en wastafel", "Aantal badkamers": "2 badkamers en 1 apart toilet", "Cv-ketel": "Intergas CW6 prestige (gas gestookt combiketel uit 2012, eigendom)", "Warm water": "Cv-ketel", "Verwarming": "Cv-ketel", "Isolatie": "Dakisolatie en gedeeltelijk dubbel glas", "Energielabel": "Niet", "Eigendomssituatie": "Volle eigendom", "Oppervlakte": 43.0, "Balkon/dakterras": "Dakterras aanwezig", "Ligging tuin": "Gelegen op het noordwesten", "Zonneterras": 12.0, "Tuin": "Zonneterras", "Ligging": "In centrum en in woonwijk", "Schuur/berging": "Inpandig", "Soort parkeergelegenheid": "Betaald parkeren", "Aangeboden sinds": "23/08/2024", "Verkoopdatum": "17/09/2024", "Looptijd": "3 weken", "link": "https://www.funda.nl/detail/koop/amsterdam/huis-westerstraat-268/43605006/", "ID": 43605006, "Kamers": 5, "Slaapkamers": 3}