{"category": "Apartment", "address": "Prinsen Bolwerk 70-RD", "neighborhood": "Stationsbuurt", "city": "Haarlem", "postcode": "2011MD", "province": "Noord-Holland", "Bijdrage VvE": 125.0, "Aanvaarding": "Per direct beschikbaar", "Status": "Verkocht onder voorbehoud", "Aangeboden sinds": "04/10/2024", "Oorspronkelijke vraagprijs": 750000.0, "Vraagprijs per m\u00b2": 5036.0, "Vraagprijs": 695000.0, "Soort dak": "Samengesteld dak bedekt met bitumineuze dakbedekking", "Specifiek": "Beschermd stads- of dorpsgezicht, dubbele bewoning aanwezig en dubbele bewoning mogelijk", "Bouwjaar": 1900, "Soort bouw": "Bestaande bouw", "Soort appartement": "Bovenwoning", "Inhoud": 458.0, "Gebouwgebonden buitenruimte": 13.0, "Wonen": 138.0, "Voorzieningen": "Glasvezelkabel en TV kabel", "Gelegen op": "2e woonlaag", "Aantal woonlagen": "2 woonlagen", "Energielabel": "E", "Eigendomssituatie": "Volle eigendom", "Balkon/dakterras": "Dakterras aanwezig", "Ligging": "In centrum en vrij uitzicht", "Soort parkeergelegenheid": "Betaald parkeren en parkeervergunningen", "Opstalverzekering": "Ja", "Onderhoudsplan": "Nee", "Reservefonds aanwezig": "Ja", "Periodieke bijdrage": 0, "Jaarlijkse vergadering": "Ja", "Inschrijving KvK": "Ja", "link": "https://www.funda.nl/detail/koop/haarlem/appartement-prinsen-bolwerk-70-rd/43625950/", "ID": 43625950, "Kamers": 4, "Slaapkamers": 3}