{"category": "House", "address": "Wyldpaed (Oast) 23", "neighborhood": "Verspreide huizen Twijzelerheide", "city": "Twijzelerheide", "postcode": "9287VM", "province": "Friesland", "Aanvaarding": "In overleg", "Status": "Beschikbaar", "Aangeboden sinds": "04/09/2024", "Oorspronkelijke vraagprijs": 1695000.0, "Vraagprijs per m\u00b2": 3815.0, "Vraagprijs": 1400000.0, "Bouwjaar": 1916, "Soort bouw": "Bestaande bouw", "Soort woonhuis": "Woonboerderij, vrijstaande woning", "Inhoud": 1.619, "Perceel": 14.735, "Wonen": 367.0, "Aantal woonlagen": "2 woonlagen", "Badkamervoorzieningen": "Douche, dubbele wastafel, ligbad, wastafel, en wastafelmeubel", "Aantal badkamers": "1 badkamer en 1 apart toilet", "Energielabel": "F", "Eigendomssituatie": "Volle eigendom", "Oppervlakte": 5.05, "Tuin": "Tuin rondom", "Ligging": "Landelijk gelegen", "Soort garage": "Parkeerplaats", "Soort parkeergelegenheid": "Op eigen terrein", "link": "https://www.funda.nl/detail/koop/twijzelerheide/huis-wyldpaed-oast-23/43664495/", "ID": 43664495, "Kamers": 4, "Slaapkamers": 2}