{"category": "Apartment", "address": "Type G1-0 | 3e verdieping (Bouwnr. 2a-88)", "neighborhood": "Camminghaburen-Zuid", "city": "Leeuwarden", "postcode": "8925AP", "province": "Friesland", "Aanvaarding": "In overleg", "Status": "Onder optie", "Aangeboden sinds": "04/09/2024", "Vraagprijs per m\u00b2": 4155.0, "Vraagprijs": 295000.0, "Bouwjaar": 2024, "Soort bouw": "Nieuwbouw", "Soort appartement": "Portiekflat (appartement)", "Inhoud": 223.0, "Gebouwgebonden buitenruimte": 7.0, "Wonen": 71.0, "Voorzieningen": "Lift en mechanische ventilatie", "Gelegen op": "4e woonlaag", "Aantal woonlagen": "1 woonlaag", "Badkamervoorzieningen": "Toilet en wastafel", "Aantal badkamers": "1 badkamer en 1 apart toilet", "Isolatie": "Volledig ge\u00efsoleerd", "Energielabel": "A", "Balkon/dakterras": "Balkon aanwezig", "Ligging": "In woonwijk", "Schuur/berging": "Inpandig", "Soort parkeergelegenheid": "Op eigen terrein", "link": "https://www.funda.nl/detail/koop/leeuwarden/appartement-type-g1-0-3e-verdieping-0-ong/43680319/", "ID": 43680319, "Kamers": 3, "Slaapkamers": 2}