{"category": "Parking", "address": "Tempeliersstraat 31", "neighborhood": "Koninginnebuurt", "city": "Haarlem", "postcode": "2012EA", "province": "Noord-Holland", "Aanvaarding": "In overleg", "Status": "Beschikbaar", "Aangeboden sinds": "04/09/2024", "Servicekosten": 11.0, "Vraagprijs": 22500.0, "Soort bouw": "Nieuwbouw", "Soort parkeergelegenheid": "Parkeerplaats", "Capaciteit": "1", "link": "https://www.funda.nl/detail/koop/haarlem/parkeergelegenheid-tempeliersstraat-31/43695113/", "ID": 43695113, "Bouwjaar": 0, "Energielabel": ""}