{"category": "Apartment", "address": "Prins Clausplein 107", "neighborhood": "Rapenburg", "city": "Leeuwarden", "postcode": "8935DE", "province": "Friesland", "Bijdrage VvE": 351.72, "Aanvaarding": "In overleg", "Status": "Beschikbaar", "Aangeboden sinds": "03/12/2024", "Oorspronkelijke vraagprijs": 400000.0, "Vraagprijs per m\u00b2": 2958.0, "Vraagprijs": 387500.0, "Soort dak": "Plat dak bedekt met bitumineuze dakbedekking", "Toegankelijkheid": "Toegankelijk voor mensen met een beperking en toegankelijk voor ouderen", "Bouwjaar": 1988, "Soort bouw": "Bestaande bouw", "Soort appartement": "Portiekflat (appartement)", "Inhoud": 398.0, "Externe bergruimte": 4.0, "Wonen": 131.0, "Voorzieningen": "Elektrische deur en elektra", "Gelegen op": "18e woonlaag", "Aantal woonlagen": "1 woonlaag", "Badkamervoorzieningen": "Toilet, 2 wastafels, en ligbad", "Aantal badkamers": "2 badkamers en 1 apart toilet", "Cv-ketel": "Intergas Kompakt HRE 24/18A (gas gestookt combiketel uit 2022, eigendom)", "Warm water": "Cv-ketel", "Verwarming": "Cv-ketel", "Isolatie": "Dakisolatie, dubbel glas, HR-glas en muurisolatie", "Energielabel": "A", "Eigendomssituatie": "Volle eigendom", "Ligging": "In woonwijk en vrij uitzicht", "Schuur/berging": "Inpandig", "Capaciteit": "1 auto", "Soort garage": "Inpandig en parkeerplaats", "Soort parkeergelegenheid": "Openbaar parkeren", "Opstalverzekering": "Ja", "Onderhoudsplan": "Ja", "Reservefonds aanwezig": "Ja", "Periodieke bijdrage": 0, "Jaarlijkse vergadering": "Ja", "Inschrijving KvK": "Ja", "link": "https://www.funda.nl/detail/koop/leeuwarden/appartement-prins-clausplein-107/43701682/", "ID": 43701682, "Kamers": 3, "Slaapkamers": 2}