{"category": "Other", "address": "Menno van Coehoornwei 31", "neighborhood": "Buitengebied Britsum", "city": "Britsum", "postcode": "9055MD", "province": "Friesland", "Aanvaarding": "In overleg", "Status": "Beschikbaar", "Aangeboden sinds": "03/12/2024", "Vraagprijs": 63500.0, "Soort bouw": "Nieuwbouw", "Soort overig aanbod": "Opslagruimte", "Afmetingen": 45.0, "Voorzieningen": "Elektrische deur, elektra en stromend water", "link": "https://www.funda.nl/detail/koop/britsum/object-menno-van-coehoornwei-31/43710976/", "ID": 43710976, "Bouwjaar": 0, "Energielabel": ""}