{"category": "Apartment", "address": "Raadhuisplein 8", "neighborhood": "Franeker Binnenstad", "city": "Franeker", "postcode": "8801KX", "province": "Friesland", "Aanvaarding": "In overleg", "Status": "Beschikbaar", "Aangeboden sinds": "02/01/2025", "Oorspronkelijke vraagprijs": 335000.0, "Vraagprijs per m\u00b2": 3060.0, "Vraagprijs": 355000.0, "Soort dak": "Plat dak bedekt met asbest en pannen", "Specifiek": "Beschermd stads- of dorpsgezicht en kluswoning", "Bouwjaar": 1895, "Soort bouw": "Bestaande bouw", "Soort appartement": "Bovenwoning", "Inhoud": 775.0, "Externe bergruimte": 60.0, "Gebouwgebonden buitenruimte": 1.0, "Overige inpandige ruimte": 173.0, "Wonen": 116.0, "Voorzieningen": "Elektra en stromend water", "Gelegen op": "2e woonlaag", "Aantal woonlagen": "3 woonlagen", "Badkamervoorzieningen": "Douche en toilet", "Aantal badkamers": "1 badkamer", "Warm water": "Geiser", "Verwarming": "Gaskachels", "Isolatie": "Geen isolatie", "Energielabel": "G", "Eigendomssituatie": "Volle eigendom", "Ligging tuin": "Gelegen op het zuidoosten bereikbaar via achterom", "Achtertuin": 165.0, "Tuin": "Achtertuin", "Ligging": "In centrum", "Schuur/berging": "Aangebouwde stenen berging", "Capaciteit": "4 auto's", "Soort garage": "Vrijstaande stenen garage", "Soort parkeergelegenheid": "Op afgesloten terrein, op eigen terrein en openbaar parkeren", "Opstalverzekering": "Nee", "Onderhoudsplan": "Nee", "Reservefonds aanwezig": "Nee", "Periodieke bijdrage": "Nee", "Jaarlijkse vergadering": "Nee", "Inschrijving KvK": "Nee", "Winkelruimte": 173.0, "link": "https://www.funda.nl/detail/koop/franeker/appartement-raadhuisplein-8/43743955/", "ID": 43743955, "Kamers": 9, "Slaapkamers": 5}