{"category": "Apartment", "address": "De Ploeg - Type B (Bouwnr. 22)", "neighborhood": "Centrum", "city": "Drachten", "postcode": "9203", "province": "Friesland", "Aanvaarding": "In overleg", "Status": "Beschikbaar", "Aangeboden sinds": "02/01/2025", "Vraagprijs per m\u00b2": 4433.0, "Vraagprijs": 297000.0, "Keurmerken": "SWK Garantiecertificaat", "Soort dak": "Plat dak bedekt met bitumineuze dakbedekking", "Bouwjaar": 2026, "Soort bouw": "Nieuwbouw", "Soort appartement": "Galerijflat (appartement)", "Inhoud": 200.0, "Externe bergruimte": 5.0, "Gebouwgebonden buitenruimte": 10.0, "Wonen": 67.0, "Voorzieningen": "Elektra", "Gelegen op": "4e woonlaag", "Aantal woonlagen": "1 woonlaag", "Aantal badkamers": "1 badkamer en 1 apart toilet", "Warm water": "Elektrische boiler", "Verwarming": "Warmte terugwininstallatie en warmtepomp", "Isolatie": "Volledig ge\u00efsoleerd", "Energielabel": "A3", "Balkon/dakterras": "Balkon aanwezig", "Ligging": "In centrum", "Schuur/berging": "Box", "Soort garage": "Parkeerplaats", "Soort parkeergelegenheid": "Op eigen terrein", "link": "https://www.funda.nl/detail/koop/drachten/appartement-de-ploeg-type-b-0-ong/43743226/", "ID": 43743226, "Kamers": 3, "Slaapkamers": 2}