{"category": "Apartment", "address": "Langew\u00e2l 28-A", "neighborhood": "Gorredijk-Centrum", "city": "Gorredijk", "postcode": "8401DE", "province": "Friesland", "Aanvaarding": "In overleg", "Status": "Verkocht onder voorbehoud", "Aangeboden sinds": "02/01/2025", "Vraagprijs per m\u00b2": 2407.0, "Vraagprijs": 399500.0, "Soort dak": "Plat dak bedekt met bitumineuze dakbedekking", "Specifiek": "Gedeeltelijk gestoffeerd", "Bouwjaar": 1993, "Soort bouw": "Bestaande bouw", "Soort appartement": "Bovenwoning (appartement)", "Inhoud": 560.0, "Gebouwgebonden buitenruimte": 70.0, "Wonen": 166.0, "Voorzieningen": "Elektra", "Gelegen op": "2e woonlaag", "Aantal woonlagen": "3 woonlagen", "Badkamervoorzieningen": "Douche, ligbad, toilet, en wastafel", "Aantal badkamers": "1 badkamer en 1 apart toilet", "Cv-ketel": "Combi (gas gestookt combiketel uit 2022, eigendom)", "Warm water": "Zonneboiler", "Verwarming": "Cv-ketel", "Isolatie": "Volledig ge\u00efsoleerd", "Energielabel": "B", "Eigendomssituatie": "Volle eigendom", "Ligging tuin": "Gelegen op het oosten", "Zonneterras": 70.0, "Tuin": "Zonneterras", "Ligging": "Aan vaarwater en in centrum", "Capaciteit": "1 auto", "Soort garage": "Vrijstaande stenen garage", "Soort parkeergelegenheid": "Openbaar parkeren", "Opstalverzekering": "Nee", "Onderhoudsplan": "Nee", "Reservefonds aanwezig": "Nee", "Periodieke bijdrage": "Nee", "Jaarlijkse vergadering": "Nee", "Inschrijving KvK": "Nee", "link": "https://www.funda.nl/detail/koop/gorredijk/appartement-langewal-28-a/43747244/", "ID": 43747244, "Kamers": 5, "Slaapkamers": 3}