{"category": "Apartment", "address": "Utrechtsestraat 88-C", "neighborhood": "Amstelveldbuurt", "city": "Amsterdam", "postcode": "1017VR", "province": "Noord-Holland", "Aanvaarding": "In overleg", "Status": "Onder bod", "Aangeboden sinds": "31/12/2024", "Vraagprijs per m\u00b2": 10938.0, "Vraagprijs": 350000.0, "Soort dak": "Samengesteld dak", "Specifiek": "Beschermd stads- of dorpsgezicht", "Bouwjaar": 1842, "Soort bouw": "Bestaande bouw", "Soort appartement": "Tussenverdieping (appartement)", "Inhoud": 104.0, "Gebouwgebonden buitenruimte": 5.0, "Wonen": 32.0, "Voorzieningen": "Mechanische ventilatie", "Gelegen op": "3e woonlaag", "Aantal woonlagen": "1 woonlaag", "Aantal badkamers": "1 badkamer en 1 apart toilet", "Cv-ketel": "HR-107 ketel (gas gestookt uit 2024, eigendom)", "Warm water": "Cv-ketel", "Verwarming": "Cv-ketel en gehele vloerverwarming", "Isolatie": "Dakisolatie, HR-glas, muurisolatie en vloerisolatie", "Energielabel": "A", "Eigendomssituatie": "Volle eigendom", "Balkon/dakterras": "Balkon aanwezig", "Ligging tuin": "Gelegen op het westen", "Zonneterras": 5.0, "Tuin": "Zonneterras", "Ligging": "Aan drukke weg en in centrum", "Soort parkeergelegenheid": "Betaald parkeren en parkeervergunningen", "Opstalverzekering": "Nee", "Onderhoudsplan": "Nee", "Reservefonds aanwezig": "Nee", "Periodieke bijdrage": "Nee", "Jaarlijkse vergadering": "Nee", "Inschrijving KvK": "Nee", "link": "https://www.funda.nl/detail/koop/amsterdam/appartement-utrechtsestraat-88-c/43745086/", "ID": 43745086, "Kamers": 2, "Slaapkamers": 1}