{"category": "House", "address": "Kadijk 4", "neighborhood": "Lemmer-Buitengebied", "city": "Lemmer", "postcode": "8531XD", "province": "Friesland", "Aanvaarding": "In overleg", "Status": "Beschikbaar", "Aangeboden sinds": "04/10/2024", "Oorspronkelijke vraagprijs": 1575000.0, "Vraagprijs per m\u00b2": 2872.0, "Vraagprijs": 675000.0, "Bouwjaar": 1993, "Soort bouw": "Bestaande bouw", "Soort woonhuis": "Eengezinswoning, vrijstaande woning (bedrijfs- of dienstwoning)", "Inhoud": 750.0, "Perceel": 1.2, "Externe bergruimte": 789.0, "Gebouwgebonden buitenruimte": 1.807, "Overige inpandige ruimte": 200.0, "Wonen": 235.0, "Voorzieningen": "Schuifpui", "Aantal woonlagen": "2 woonlagen en een kelder", "Badkamervoorzieningen": "2 douches, 2 dubbele wastafels, 2 ligbaden, en 2 toiletten", "Aantal badkamers": "2 badkamers en 3 aparte toiletten", "Warm water": "Gasboiler", "Verwarming": "Heteluchtverwarming", "Isolatie": "Volledig ge\u00efsoleerd", "Energielabel": "B", "Oppervlakte": 1.2, "Tuin": "Tuin rondom", "Ligging": "Bedrijventerrein", "Soort parkeergelegenheid": "Op eigen terrein", "Bedrijfsruimte": "(vrijstaand)", "link": "https://www.funda.nl/detail/koop/lemmer/huis-kadijk-4/43757823/", "ID": 43757823, "Kamers": 5, "Slaapkamers": 3}