{"category": "Apartment", "address": "Zeeburgerkade 720", "neighborhood": "Architectenbuurt", "city": "Amsterdam", "postcode": "1019HT", "province": "Noord-Holland", "Bijdrage VvE": 294.22, "Status": "Verkocht", "Vraagprijs per m\u00b2": 7080.0, "Laatste vraagprijs": 800000.0, "Soort dak": "Samengesteld dak", "Specifiek": "Gestoffeerd", "Bouwjaar": 1889, "Soort bouw": "Bestaande bouw", "Soort appartement": "Bovenwoning (appartement)", "Inhoud": 398.0, "Externe bergruimte": 4.0, "Gebouwgebonden buitenruimte": 35.0, "Wonen": 113.0, "Voorzieningen": "Elektra", "Gelegen op": "1e woonlaag", "Aantal woonlagen": "1 woonlaag", "Badkamervoorzieningen": "Douche, dubbele wastafel, inloopdouche, ligbad, en toilet", "Aantal badkamers": "1 badkamer", "Cv-ketel": "Remeha (gas gestookt combiketel uit 2016, eigendom)", "Warm water": "Cv-ketel", "Verwarming": "Cv-ketel", "Isolatie": "Dubbel glas en volledig ge\u00efsoleerd", "Energielabel": "B", "Lasten": "Eeuwigdurend afgekocht", "Eigendomssituatie": "Gemeentelijk eigendom belast met erfpacht (einddatum erfpacht: 31-10-2039)", "Balkon/dakterras": "Dakterras aanwezig en balkon aanwezig", "Ligging": "Aan park, aan vaarwater, aan water en vrij uitzicht", "Schuur/berging": "Box", "Soort parkeergelegenheid": "Betaald parkeren, openbaar parkeren en parkeervergunningen", "Opstalverzekering": "Ja", "Onderhoudsplan": "Ja", "Reservefonds aanwezig": "Ja", "Periodieke bijdrage": 0, "Jaarlijkse vergadering": "Ja", "Inschrijving KvK": "Ja", "Aangeboden sinds": "30/10/2024", "Verkoopdatum": "04/12/2024", "Looptijd": "5 weken", "link": "https://www.funda.nl/detail/koop/amsterdam/appartement-zeeburgerkade-720/43781036/", "ID": 43781036, "Kamers": 2, "Slaapkamers": 1}