{"category": "House", "address": "Spanjaardslaan 24", "neighborhood": "Rengerspark", "city": "Leeuwarden", "postcode": "8917AT", "province": "Friesland", "Aanvaarding": "In overleg", "Status": "Onder bod", "Aangeboden sinds": "03/11/2024", "Vraagprijs per m\u00b2": 3205.0, "Vraagprijs": 359000.0, "Soort dak": "Zadeldak bedekt met pannen", "Bouwjaar": 1934, "Soort bouw": "Bestaande bouw", "Soort woonhuis": "Eengezinswoning, tussenwoning", "Inhoud": 427.0, "Perceel": 146.0, "Externe bergruimte": 3.0, "Gebouwgebonden buitenruimte": 13.0, "Wonen": 112.0, "Voorzieningen": "Dakraam, glasvezelkabel, natuurlijke ventilatie, rookkanaal, en TV kabel", "Aantal woonlagen": "2 woonlagen en een zolder", "Badkamervoorzieningen": "Douche, toilet, en wastafel", "Aantal badkamers": "1 badkamer en 1 apart toilet", "Cv-ketel": "Nefit HR (gas gestookt combiketel uit 2024, eigendom)", "Warm water": "Cv-ketel", "Verwarming": "Cv-ketel en gaskachels", "Isolatie": "Dakisolatie en grotendeels dubbelglas", "Energielabel": "C", "Eigendomssituatie": "Volle eigendom", "Oppervlakte": 146.0, "Balkon/dakterras": "Balkon aanwezig", "Ligging tuin": "Gelegen op het noorden bereikbaar via achterom", "Achtertuin": 36.0, "Tuin": "Achtertuin en voortuin", "Ligging": "Aan drukke weg en in woonwijk", "Schuur/berging": "Aangebouwde houten berging", "Soort parkeergelegenheid": "Openbaar parkeren en parkeervergunningen", "link": "https://www.funda.nl/detail/koop/leeuwarden/huis-spanjaardslaan-24/43783371/", "ID": 43783371, "Kamers": 5, "Slaapkamers": 4}