{"category": "Apartment", "address": "Voorstreek 4-B", "neighborhood": "De Waag", "city": "Leeuwarden", "postcode": "8911JN", "province": "Friesland", "Bijdrage VvE": 50.0, "Aanvaarding": "Per direct beschikbaar", "Status": "Beschikbaar", "Aangeboden sinds": "19/02/2025", "Vraagprijs per m\u00b2": 4044.0, "Vraagprijs": 315400.0, "Bouwjaar": 1890, "Soort bouw": "Bestaande bouw", "Soort appartement": "Galerijflat (appartement)", "Inhoud": 311.0, "Gebouwgebonden buitenruimte": 13.0, "Wonen": 78.0, "Gelegen op": "1e woonlaag", "Aantal woonlagen": "1 woonlaag", "Energielabel": "A1", "Ligging": "In centrum", "Opstalverzekering": "Ja", "Onderhoudsplan": "Nee", "Reservefonds aanwezig": "Nee", "Periodieke bijdrage": 0, "Jaarlijkse vergadering": "Nee", "Inschrijving KvK": "Ja", "link": "https://www.funda.nl/detail/koop/leeuwarden/appartement-voorstreek-4-b/43804034/", "ID": 43804034, "Kamers": 4, "Slaapkamers": 2}