{"category": "Apartment", "address": "Schoterweg 35-A", "neighborhood": "Frans Halsbuurt", "city": "Haarlem", "postcode": "2021HZ", "province": "Noord-Holland", "Bijdrage VvE": 95.0, "Aanvaarding": "In overleg", "Status": "Verkocht onder voorbehoud", "Aangeboden sinds": "17/02/2025", "Servicekosten": 95.0, "Vraagprijs per m\u00b2": 7353.0, "Vraagprijs": 375000.0, "Soort dak": "Plat dak bedekt met bitumineuze dakbedekking", "Specifiek": "Beschermd stads- of dorpsgezicht", "Bouwjaar": 1980, "Soort bouw": "Bestaande bouw", "Soort appartement": "Portiekflat (appartement)", "Inhoud": 168.0, "Gebouwgebonden buitenruimte": 6.0, "Overige inpandige ruimte": 1.0, "Wonen": 51.0, "Voorzieningen": "Glasvezelkabel", "Gelegen op": "1e woonlaag", "Aantal woonlagen": "1 woonlaag", "Badkamervoorzieningen": "Inloopdouche, toilet, en wastafelmeubel", "Aantal badkamers": "1 badkamer", "Cv-ketel": "Gas gestookt combiketel, eigendom", "Warm water": "Cv-ketel", "Verwarming": "Cv-ketel", "Isolatie": "Dubbel glas", "Energielabel": "B", "Eigendomssituatie": "Volle eigendom", "Balkon/dakterras": "Balkon aanwezig", "Ligging": "In woonwijk", "Schuur/berging": "Inpandig", "Soort parkeergelegenheid": "Parkeervergunningen", "Opstalverzekering": "Ja", "Onderhoudsplan": "Nee", "Reservefonds aanwezig": "Ja", "Periodieke bijdrage": 0, "Jaarlijkse vergadering": "Ja", "Inschrijving KvK": "Ja", "link": "https://www.funda.nl/detail/koop/haarlem/appartement-schoterweg-35-a/43805184/", "ID": 43805184, "Kamers": 3, "Slaapkamers": 2}