{"category": "Apartment", "address": "Generaal Joubertstraat 17-A", "neighborhood": "Nelson Mandelabuurt", "city": "Haarlem", "postcode": "2021XA", "province": "Noord-Holland", "Aanvaarding": "In overleg, No-Risk clausule mogelijk", "Status": "Beschikbaar", "Aangeboden sinds": "17/02/2025", "Vraagprijs per m\u00b2": 5319.0, "Vraagprijs": 250000.0, "Soort dak": "Mansarde dak bedekt met pannen", "Specifiek": "Gedeeltelijk gestoffeerd", "Bouwjaar": 1906, "Soort bouw": "Bestaande bouw", "Soort appartement": "Tussenverdieping (appartement)", "Inhoud": 154.0, "Wonen": 47.0, "Voorzieningen": "Natuurlijke ventilatie en TV kabel", "Gelegen op": "2e woonlaag", "Aantal woonlagen": "1 woonlaag", "Badkamervoorzieningen": "Ligbad en wastafel", "Aantal badkamers": "1 badkamer", "Cv-ketel": "Intergas (gas gestookt combiketel uit 2011, eigendom)", "Warm water": "Cv-ketel", "Verwarming": "Cv-ketel", "Isolatie": "Gedeeltelijk dubbel glas", "Energielabel": "D", "Eigendomssituatie": "Volle eigendom", "Ligging": "In centrum en in woonwijk", "Soort parkeergelegenheid": "Betaald parkeren en parkeervergunningen", "Opstalverzekering": "Ja", "Onderhoudsplan": "Nee", "Reservefonds aanwezig": "Nee", "Periodieke bijdrage": "Nee", "Jaarlijkse vergadering": "Nee", "Inschrijving KvK": "Ja", "link": "https://www.funda.nl/detail/koop/haarlem/appartement-generaal-joubertstraat-17-a/43807797/", "ID": 43807797, "Kamers": 2, "Slaapkamers": 1}