{"category": "Apartment", "address": "Prins Bernhardlaan 2-S", "neighborhood": "Cremerbuurt", "city": "Haarlem", "postcode": "2032HA", "province": "Noord-Holland", "Bijdrage VvE": 150.0, "Aanvaarding": "In overleg, No-Risk clausule mogelijk", "Status": "Beschikbaar", "Aangeboden sinds": "26/02/2025", "Vraagprijs per m\u00b2": 5422.0, "Vraagprijs": 450000.0, "Soort dak": "Plat dak", "Specifiek": "Gedeeltelijk gestoffeerd", "Toegankelijkheid": "Toegankelijk voor mensen met een beperking en toegankelijk voor ouderen", "Bouwjaar": 1969, "Soort bouw": "Bestaande bouw", "Soort appartement": "Portiekflat (appartement)", "Inhoud": 257.0, "Externe bergruimte": 4.0, "Wonen": 83.0, "Voorzieningen": "Glasvezelkabel, lift, mechanische ventilatie, natuurlijke ventilatie, en TV kabel", "Gelegen op": "6e woonlaag", "Aantal woonlagen": "1 woonlaag", "Badkamervoorzieningen": "Douche en wastafel", "Aantal badkamers": "1 badkamer en 1 apart toilet", "Cv-ketel": "Intergas Kompakt HRE (gas gestookt combiketel uit 2018, eigendom)", "Warm water": "Cv-ketel", "Verwarming": "Cv-ketel", "Isolatie": "Dakisolatie, HR-glas, muurisolatie en vloerisolatie", "Energielabel": "A", "Eigendomssituatie": "Volle eigendom", "Ligging": "In woonwijk en vrij uitzicht", "Schuur/berging": "Inpandig", "Soort garage": "Parkeerkelder", "Soort parkeergelegenheid": "Openbaar parkeren en parkeergarage", "Opstalverzekering": "Ja", "Onderhoudsplan": "Ja", "Reservefonds aanwezig": "Ja", "Periodieke bijdrage": 0, "Jaarlijkse vergadering": "Ja", "Inschrijving KvK": "Ja", "link": "https://www.funda.nl/detail/koop/haarlem/appartement-prins-bernhardlaan-2-s/43811317/", "ID": 43811317, "Kamers": 3, "Slaapkamers": 2}