{"category": "Apartment", "address": "P.C. Boutensstraat 195", "neighborhood": "Van Schendelbuurt", "city": "Haarlem", "postcode": "2025LE", "province": "Noord-Holland", "Bijdrage VvE": 218.21, "Aanvaarding": "In overleg", "Status": "Beschikbaar", "Aangeboden sinds": "24/02/2025", "Vraagprijs per m\u00b2": 4412.0, "Vraagprijs": 375000.0, "Bouwjaar": 1965, "Soort bouw": "Bestaande bouw", "Soort appartement": "Portiekflat (appartement)", "Inhoud": 276.0, "Externe bergruimte": 4.0, "Gebouwgebonden buitenruimte": 10.0, "Wonen": 85.0, "Voorzieningen": "Lift", "Gelegen op": "9e woonlaag", "Aantal woonlagen": "1 woonlaag", "Badkamervoorzieningen": "Douche en wastafelmeubel", "Aantal badkamers": "1 badkamer en 1 apart toilet", "Warm water": "Elektrische boiler", "Verwarming": "Blokverwarming", "Isolatie": "Dubbel glas en muurisolatie", "Energielabel": "C", "Eigendomssituatie": "Volle eigendom", "Balkon/dakterras": "Balkon aanwezig", "Ligging": "Vrij uitzicht", "Schuur/berging": "Inpandig", "Soort parkeergelegenheid": "Openbaar parkeren", "Opstalverzekering": "Ja", "Onderhoudsplan": "Ja", "Reservefonds aanwezig": "Ja", "Periodieke bijdrage": 0, "Jaarlijkse vergadering": "Ja", "Inschrijving KvK": "Ja", "link": "https://www.funda.nl/detail/koop/haarlem/appartement-pc-boutensstraat-195/43810277/", "ID": 43810277, "Kamers": 4, "Slaapkamers": 3}