{"category": "Apartment", "address": "Leidsevaart 370-RD", "neighborhood": "Natuurkundigenbuurt-oost", "city": "Haarlem", "postcode": "2014HL", "province": "Noord-Holland", "Aanvaarding": "In overleg", "Status": "Beschikbaar", "Aangeboden sinds": "25/02/2025", "Vraagprijs per m\u00b2": 5056.0, "Vraagprijs": 450000.0, "Keurmerken": "Bouwkundige Keuring", "Soort dak": "Plat dak bedekt met bitumineuze dakbedekking", "Specifiek": "Gedeeltelijk gestoffeerd", "Bouwjaar": 1918, "Soort bouw": "Bestaande bouw", "Soort appartement": "Bovenwoning (open portiek)", "Inhoud": 300.0, "Gebouwgebonden buitenruimte": 30.0, "Wonen": 89.0, "Voorzieningen": "Airconditioning, buitenzonwering, en natuurlijke ventilatie", "Gelegen op": "2e woonlaag", "Aantal woonlagen": "2 woonlagen", "Badkamervoorzieningen": "Douche en wastafel", "Aantal badkamers": "1 badkamer en 1 apart toilet", "Cv-ketel": "Intergas (gas gestookt combiketel uit 2007, lease)", "Warm water": "Cv-ketel", "Verwarming": "Cv-ketel", "Isolatie": "Gedeeltelijk dubbel glas", "Energielabel": "D", "Eigendomssituatie": "Volle eigendom", "Balkon/dakterras": "Dakterras aanwezig", "Ligging": "Aan water en in woonwijk", "Soort parkeergelegenheid": "Openbaar parkeren", "Opstalverzekering": "Nee", "Onderhoudsplan": "Nee", "Reservefonds aanwezig": "Nee", "Periodieke bijdrage": "Nee", "Jaarlijkse vergadering": "Nee", "Inschrijving KvK": "Ja", "link": "https://www.funda.nl/detail/koop/haarlem/appartement-leidsevaart-370-rd/43810092/", "ID": 43810092, "Kamers": 4, "Slaapkamers": 3}