{"category": "House", "address": "Willem Koningstraat 14", "neighborhood": "Franeker It Stiselplak", "city": "Franeker", "postcode": "8801GZ", "province": "Friesland", "Aanvaarding": "In overleg", "Status": "Beschikbaar", "Aangeboden sinds": "28/02/2025", "Vraagprijs per m\u00b2": 2926.0, "Vraagprijs": 275000.0, "Soort dak": "Dwarskap bedekt met pannen", "Bouwjaar": 1959, "Soort bouw": "Bestaande bouw", "Soort woonhuis": "Eengezinswoning, hoekwoning", "Inhoud": 360.0, "Perceel": 256.0, "Externe bergruimte": 23.0, "Overige inpandige ruimte": 14.0, "Wonen": 94.0, "Voorzieningen": "Elektra", "Aantal woonlagen": "2 woonlagen en een zolder", "Badkamervoorzieningen": "Douche en wastafel", "Aantal badkamers": "1 badkamer en 1 apart toilet", "Cv-ketel": "Remeha Avanta 28C (gas gestookt combiketel uit 2019, eigendom)", "Warm water": "Cv-ketel", "Verwarming": "Cv-ketel", "Isolatie": "Dakisolatie, dubbel glas en muurisolatie", "Energielabel": "C", "Eigendomssituatie": "Volle eigendom", "Oppervlakte": 256.0, "Ligging tuin": "Gelegen op het noorden bereikbaar via achterom", "Achtertuin": 76.0, "Tuin": "Achtertuin en voortuin", "Ligging": "Aan rustige weg en in woonwijk", "Schuur/berging": "Vrijstaande houten berging", "Capaciteit": "1 auto", "Soort garage": "Vrijstaande stenen garage", "Soort parkeergelegenheid": "Op eigen terrein en openbaar parkeren", "link": "https://www.funda.nl/detail/koop/franeker/huis-willem-koningstraat-14/43826450/", "ID": 43826450, "Kamers": 4, "Slaapkamers": 3}