{"category": "House", "address": "Hoofden 44", "neighborhood": "De Domp", "city": "Sneek", "postcode": "8604DH", "province": "Friesland", "Aanvaarding": "In overleg", "Status": "Verkocht onder voorbehoud", "Aangeboden sinds": "02/01/2025", "Vraagprijs per m\u00b2": 4173.0, "Vraagprijs": 580000.0, "Soort dak": "Plat dak", "Toegankelijkheid": "Toegankelijk voor mensen met een beperking en toegankelijk voor ouderen", "Bouwjaar": 2009, "Soort bouw": "Bestaande bouw", "Soort woonhuis": "Bungalow, vrijstaande woning", "Inhoud": 531.0, "Perceel": 227.0, "Gebouwgebonden buitenruimte": 23.0, "Wonen": 139.0, "Voorzieningen": "Mechanische ventilatie, natuurlijke ventilatie, en TV kabel", "Aantal woonlagen": "2 woonlagen", "Badkamervoorzieningen": "Douche, toilet, en wastafel", "Aantal badkamers": "1 badkamer en 1 apart toilet", "Cv-ketel": "Intergas (gas gestookt combiketel uit 2020, eigendom)", "Warm water": "Cv-ketel", "Verwarming": "Cv-ketel", "Isolatie": "Volledig ge\u00efsoleerd", "Energielabel": "B", "Eigendomssituatie": "Volle eigendom", "Oppervlakte": 156.0, "Ligging tuin": "Gelegen op het noordwesten", "Patio/atrium": 23.0, "Tuin": "Patio/atrium", "Ligging": "Aan rustige weg en in woonwijk", "Soort parkeergelegenheid": "Openbaar parkeren", "link": "https://www.funda.nl/detail/koop/sneek/huis-hoofden-44/43851788/", "ID": 43851788, "Kamers": 4, "Slaapkamers": 3}