{"category": "House", "address": "Zwanebloem 5", "neighborhood": "Aldl\u00e2n-Oost", "city": "Leeuwarden", "postcode": "8935NZ", "province": "Friesland", "Aanvaarding": "In overleg", "Status": "Verkocht onder voorbehoud", "Aangeboden sinds": "13/01/2025", "Vraagprijs per m\u00b2": 3869.0, "Vraagprijs": 650000.0, "Bouwjaar": 1977, "Soort bouw": "Bestaande bouw", "Soort woonhuis": "Eengezinswoning, vrijstaande woning", "Inhoud": 700.0, "Perceel": 465.0, "Externe bergruimte": 8.0, "Gebouwgebonden buitenruimte": 3.0, "Overige inpandige ruimte": 25.0, "Wonen": 168.0, "Voorzieningen": "Zonnepanelen", "Aantal woonlagen": "2 woonlagen en een vliering", "Badkamervoorzieningen": "2 douches, wastafel, dubbele wastafel, en ligbad", "Aantal badkamers": "2 badkamers en 2 aparte toiletten", "Cv-ketel": "Vaillant Ecotec Plus (gas gestookt combiketel uit 2017, eigendom)", "Warm water": "Cv-ketel", "Verwarming": "Cv-ketel", "Isolatie": "Volledig ge\u00efsoleerd", "Energielabel": "B", "Eigendomssituatie": "Volle eigendom", "Oppervlakte": 465.0, "Balkon/dakterras": "Balkon aanwezig", "Tuin": "Tuin rondom", "Ligging": "Aan vaarwater, aan water, beschutte ligging, in woonwijk en vrij uitzicht", "Schuur/berging": "Aangebouwde houten berging", "Capaciteit": "1 auto", "Soort garage": "Aangebouwde stenen garage", "Soort parkeergelegenheid": "Op eigen terrein", "link": "https://www.funda.nl/detail/koop/leeuwarden/huis-zwanebloem-5/43865959/", "ID": 43865959, "Kamers": 6, "Slaapkamers": 5}