{"category": "Apartment", "address": "Zandvoorter Allee 54", "neighborhood": "Bosch en Vaart", "city": "Haarlem", "postcode": "2012WB", "province": "Noord-Holland", "Bijdrage VvE": 441.87, "Aanvaarding": "In overleg", "Status": "Beschikbaar", "Aangeboden sinds": "27/01/2025", "Vraagprijs per m\u00b2": 4574.0, "Vraagprijs": 279000.0, "Soort dak": "Plat dak bedekt met bitumineuze dakbedekking", "Toegankelijkheid": "Toegankelijk voor mensen met een beperking en toegankelijk voor ouderen", "Bouwjaar": 1967, "Soort bouw": "Bestaande bouw", "Soort appartement": "Portiekflat (corridorflat)", "Inhoud": 200.0, "Externe bergruimte": 2.0, "Gebouwgebonden buitenruimte": 3.0, "Overige inpandige ruimte": 1.0, "Wonen": 61.0, "Voorzieningen": "Elektra", "Gelegen op": "1e woonlaag", "Aantal woonlagen": "1 woonlaag", "Badkamervoorzieningen": "Douche en wastafel", "Aantal badkamers": "1 badkamer en 1 apart toilet", "Warm water": "Elektrische boiler", "Verwarming": "Blokverwarming", "Isolatie": "Dubbel glas", "Energielabel": "E", "Eigendomssituatie": "Volle eigendom", "Ligging": "In woonwijk", "Schuur/berging": "Aangebouwde stenen berging", "Soort parkeergelegenheid": "Openbaar parkeren", "Opstalverzekering": "Ja", "Onderhoudsplan": "Ja", "Reservefonds aanwezig": "Ja", "Periodieke bijdrage": 0, "Jaarlijkse vergadering": "Ja", "Inschrijving KvK": "Ja", "link": "https://www.funda.nl/detail/koop/haarlem/appartement-zandvoorter-allee-54/43871094/", "ID": 43871094, "Kamers": 2, "Slaapkamers": 1}