{"category": "House", "address": "Paulus Potterstraat 19-B", "neighborhood": "Wolvega-Schildersbuurt", "city": "Wolvega", "postcode": "8471VN", "province": "Friesland", "Aanvaarding": "In overleg", "Status": "Verkocht onder voorbehoud", "Aangeboden sinds": "27/01/2025", "Vraagprijs per m\u00b2": 3667.0, "Vraagprijs": 275000.0, "Soort dak": "Zadeldak bedekt met pannen", "Bouwperiode": "2011-2020", "Soort bouw": "Bestaande bouw", "Soort woonhuis": "Eengezinswoning, tussenwoning", "Inhoud": 299.0, "Externe bergruimte": 11.0, "Overige inpandige ruimte": 10.0, "Wonen": 75.0, "Voorzieningen": "Elektra", "Aantal woonlagen": "2 woonlagen en een zolder", "Badkamervoorzieningen": "Douche, toilet, vloerverwarming, en wastafelmeubel", "Aantal badkamers": "1 badkamer en 1 apart toilet", "Cv-ketel": "Intergas (gas gestookt combiketel uit 2013, eigendom)", "Warm water": "Zonneboiler", "Verwarming": "Cv-ketel", "Isolatie": "HR-glas en volledig ge\u00efsoleerd", "Energielabel": "A", "Eigendomssituatie": "Volle eigendom", "Oppervlakte": 1.0, "Ligging tuin": "Gelegen op het zuiden bereikbaar via achterom", "Achtertuin": 55.0, "Tuin": "Achtertuin en voortuin", "Ligging": "Aan rustige weg en in woonwijk", "Schuur/berging": "Vrijstaande houten berging", "Soort parkeergelegenheid": "Openbaar parkeren", "link": "https://www.funda.nl/detail/koop/wolvega/huis-paulus-potterstraat-19-b/43885660/", "ID": 43885660, "Bouwjaar": 0, "Kamers": 3, "Slaapkamers": 2}