{"category": "Apartment", "address": "Raadhuisplein 186", "neighborhood": "Centrum", "city": "Drachten", "postcode": "9203EC", "province": "Friesland", "Bijdrage VvE": 238.25, "Aanvaarding": "In overleg", "Status": "Verkocht onder voorbehoud", "Aangeboden sinds": "27/01/2025", "Vraagprijs per m\u00b2": 3191.0, "Vraagprijs": 300000.0, "Soort dak": "Plat dak bedekt met bitumineuze dakbedekking", "Bouwjaar": 1968, "Soort bouw": "Bestaande bouw", "Soort appartement": "Galerijflat", "Inhoud": 309.0, "Externe bergruimte": 7.0, "Gebouwgebonden buitenruimte": 8.0, "Wonen": 94.0, "Voorzieningen": "Lift en TV kabel", "Gelegen op": "5e woonlaag", "Aantal woonlagen": "6 woonlagen", "Badkamervoorzieningen": "Douche en wastafel", "Aantal badkamers": "1 badkamer en 1 apart toilet", "Cv-ketel": "Remeha (gas gestookt combiketel uit 2006, eigendom)", "Warm water": "Cv-ketel", "Verwarming": "Cv-ketel", "Isolatie": "Driedubbel glas en muurisolatie", "Energielabel": "B", "Eigendomssituatie": "Volle eigendom", "Balkon/dakterras": "Balkon aanwezig", "Ligging": "In centrum", "Schuur/berging": "Box", "Soort parkeergelegenheid": "Parkeergarage en parkeervergunningen", "Opstalverzekering": "Ja", "Onderhoudsplan": "Ja", "Reservefonds aanwezig": "Ja", "Periodieke bijdrage": 0, "Jaarlijkse vergadering": "Ja", "Inschrijving KvK": "Ja", "link": "https://www.funda.nl/detail/koop/drachten/appartement-raadhuisplein-186/43885586/", "ID": 43885586, "Kamers": 4, "Slaapkamers": 3}