{"category": "House", "address": "Schoterlandseweg 102", "neighborhood": "Oudehorne", "city": "Oudehorne", "postcode": "8413NE", "province": "Friesland", "Aanvaarding": "In overleg", "Status": "Verkocht onder voorbehoud", "Aangeboden sinds": "27/01/2025", "Vraagprijs per m\u00b2": 3431.0, "Vraagprijs": 525000.0, "Soort dak": "Samengesteld dak bedekt met bitumineuze dakbedekking en pannen", "Specifiek": "Gedeeltelijk gestoffeerd", "Bouwjaar": 1900, "Soort bouw": "Bestaande bouw", "Soort woonhuis": "Eengezinswoning, vrijstaande woning", "Inhoud": 500.0, "Perceel": 5.645, "Externe bergruimte": 640.0, "Overige inpandige ruimte": 21.0, "Wonen": 153.0, "Aantal woonlagen": "2 woonlagen en een zolder", "Badkamervoorzieningen": "Douche en dubbele wastafel", "Aantal badkamers": "1 badkamer en 2 aparte toiletten", "Cv-ketel": "Atag (gas gestookt combiketel uit 2001, eigendom)", "Warm water": "Cv-ketel", "Verwarming": "Cv-ketel", "Isolatie": "Gedeeltelijk dubbel glas", "Energielabel": "G", "Eigendomssituatie": "Volle eigendom", "Oppervlakte": 5.645, "Tuin": "Tuin rondom", "Ligging": "Aan drukke weg, buiten bebouwde kom, in bosrijke omgeving, landelijk gelegen en vrij uitzicht", "Schuur/berging": "Vrijstaande stenen berging", "Voorzieningen": "Elektra", "Capaciteit": "1 auto", "Soort garage": "Inpandig", "Soort parkeergelegenheid": "Op eigen terrein", "link": "https://www.funda.nl/detail/koop/oudehorne/huis-schoterlandseweg-102/43886920/", "ID": 43886920, "Kamers": 6, "Slaapkamers": 4}