{"category": "House", "address": "Hanebalken 2", "neighborhood": "De Trisken", "city": "Drachten", "postcode": "9205CX", "province": "Friesland", "Aanvaarding": "In overleg", "Status": "Verkocht onder voorbehoud", "Aangeboden sinds": "10/02/2025", "Vraagprijs per m\u00b2": 3123.0, "Vraagprijs": 368500.0, "Soort dak": "Zadeldak bedekt met pannen", "Bouwjaar": 1991, "Soort bouw": "Bestaande bouw", "Soort woonhuis": "Eengezinswoning, 2-onder-1-kapwoning", "Inhoud": 474.0, "Perceel": 404.0, "Gebouwgebonden buitenruimte": 5.0, "Overige inpandige ruimte": 21.0, "Wonen": 118.0, "Aantal woonlagen": "3 woonlagen", "Badkamervoorzieningen": "Inloopdouche, toilet, en wastafelmeubel", "Aantal badkamers": "1 badkamer en 1 apart toilet", "Cv-ketel": "Intergas HRE (gas gestookt combiketel uit 2010, eigendom)", "Warm water": "Cv-ketel", "Verwarming": "Cv-ketel", "Isolatie": "Dakisolatie, HR-glas, muurisolatie en vloerisolatie", "Energielabel": "B", "Eigendomssituatie": "Volle eigendom", "Oppervlakte": 404.0, "Ligging tuin": "Gelegen op het noordwesten bereikbaar via achterom", "Achtertuin": 74.0, "Tuin": "Achtertuin, voortuin en zijtuin", "Ligging": "Aan rustige weg en in woonwijk", "Voorzieningen": "Elektra", "Capaciteit": "1 auto", "Soort garage": "Aangebouwde stenen garage", "Soort parkeergelegenheid": "Op eigen terrein", "link": "https://www.funda.nl/detail/koop/drachten/huis-hanebalken-2/43897939/", "ID": 43897939, "Kamers": 5, "Slaapkamers": 4}