{"category": "Apartment", "address": "Lange Wijngaardstraat 25-RD", "neighborhood": "Bakenes", "city": "Haarlem", "postcode": "2011RK", "province": "Noord-Holland", "Aanvaarding": "In overleg", "Status": "Beschikbaar", "Aangeboden sinds": "10/02/2025", "Vraagprijs per m\u00b2": 4657.0, "Vraagprijs": 475000.0, "Soort dak": "Samengesteld dak bedekt met bitumineuze dakbedekking en overig", "Specifiek": "Beschermd stads- of dorpsgezicht", "Bouwjaar": 1900, "Soort bouw": "Bestaande bouw", "Soort appartement": "Bovenwoning (appartement)", "Inhoud": 361.0, "Gebouwgebonden buitenruimte": 24.0, "Overige inpandige ruimte": 3.0, "Wonen": 102.0, "Aantal woonlagen": "2 woonlagen en een vliering", "Aantal badkamers": "1 badkamer en 1 apart toilet", "Cv-ketel": "Intergas Komi Kompakt (gas gestookt combiketel uit 2007, eigendom)", "Warm water": "Cv-ketel", "Verwarming": "Cv-ketel", "Isolatie": "Gedeeltelijk dubbel glas", "Energielabel": "D", "Eigendomssituatie": "Volle eigendom", "Balkon/dakterras": "Dakterras aanwezig", "Ligging": "Beschutte ligging en in centrum", "Soort parkeergelegenheid": "Parkeergarage en parkeervergunningen", "Opstalverzekering": "Ja", "Onderhoudsplan": "Nee", "Reservefonds aanwezig": "Nee", "Periodieke bijdrage": "Nee", "Jaarlijkse vergadering": "Nee", "Inschrijving KvK": "Ja", "link": "https://www.funda.nl/detail/koop/haarlem/appartement-lange-wijngaardstraat-25-rd/43896069/", "ID": 43896069, "Kamers": 5, "Slaapkamers": 4}