{"category": "House", "address": "Oudeweg 107", "neighborhood": "De Swetten", "city": "Drachten", "postcode": "9201EK", "province": "Friesland", "Aanvaarding": "In overleg", "Status": "Beschikbaar", "Aangeboden sinds": "10/02/2025", "Vraagprijs per m\u00b2": 3421.0, "Vraagprijs": 325000.0, "Soort dak": "Zadeldak bedekt met pannen", "Bouwjaar": 1925, "Soort bouw": "Bestaande bouw", "Soort woonhuis": "Eengezinswoning, vrijstaande woning", "Inhoud": 352.0, "Perceel": 292.0, "Externe bergruimte": 6.0, "Gebouwgebonden buitenruimte": 9.0, "Wonen": 95.0, "Voorzieningen": "Elektra", "Aantal woonlagen": "2 woonlagen en een vliering", "Badkamervoorzieningen": "2 douches en ligbad", "Aantal badkamers": "2 badkamers", "Cv-ketel": "Nefit Trendline (gas gestookt combiketel uit 2016, eigendom)", "Warm water": "Cv-ketel", "Verwarming": "Cv-ketel", "Energielabel": "E", "Eigendomssituatie": "Volle eigendom", "Oppervlakte": 292.0, "Tuin": "Tuin rondom", "Ligging": "In centrum en in woonwijk", "Schuur/berging": "Vrijstaande stenen berging", "link": "https://www.funda.nl/detail/koop/drachten/huis-oudeweg-107/43892246/", "ID": 43892246, "Kamers": 6, "Slaapkamers": 5}