{"category": "House", "address": "Molenfenne 8", "neighborhood": "Warfstermolen", "city": "Warfstermolen", "postcode": "9852TL", "province": "Friesland", "Aanvaarding": "In overleg", "Status": "Beschikbaar", "Aangeboden sinds": "10/02/2025", "Vraagprijs per m\u00b2": 3353.0, "Vraagprijs": 479500.0, "Soort dak": "Zadeldak bedekt met bitumineuze dakbedekking en pannen", "Toegankelijkheid": "Aangepaste woning", "Bouwjaar": 2001, "Soort bouw": "Bestaande bouw", "Soort woonhuis": "Eengezinswoning, vrijstaande woning", "Inhoud": 532.0, "Perceel": 1.4, "Externe bergruimte": 12.0, "Gebouwgebonden buitenruimte": 9.0, "Overige inpandige ruimte": 8.0, "Wonen": 143.0, "Voorzieningen": "Zonnepanelen", "Aantal woonlagen": "2 woonlagen", "Badkamervoorzieningen": "2 douches, toilet, 2 wastafels, en ligbad", "Aantal badkamers": "2 badkamers en 1 apart toilet", "Cv-ketel": "Gas gestookt combiketel, eigendom", "Warm water": "Cv-ketel", "Verwarming": "Cv-ketel en gedeeltelijke vloerverwarming", "Energielabel": "B", "Eigendomssituatie": "Volle eigendom", "Oppervlakte": 1.4, "Tuin": "Tuin rondom", "Schuur/berging": "Vrijstaande houten berging", "Soort parkeergelegenheid": "Op eigen terrein", "link": "https://www.funda.nl/detail/koop/warfstermolen/huis-molenfenne-8/43890660/", "ID": 43890660, "Kamers": 5, "Slaapkamers": 4}